{
    "mode": "Perform",
    "ml_task": "multiclass_classification",
    "results_path": "automl_stereo",
    "total_time_limit": 3600,
    "model_time_limit": null,
    "algorithms": [
        "Xgboost",
        "Random Forest",
        "CatBoost"
    ],
    "train_ensemble": true,
    "stack_models": false,
    "eval_metric": "logloss",
    "validation_strategy": {
        "validation_type": "kfold",
        "k_folds": 5,
        "shuffle": true,
        "stratify": true,
        "X_path": "automl_stereo/X.data",
        "y_path": "automl_stereo/y.data",
        "results_path": "automl_stereo"
    },
    "verbose": 1,
    "explain_level": 2,
    "golden_features": false,
    "features_selection": true,
    "start_random_models": 5,
    "hill_climbing_steps": 2,
    "top_models_to_improve": 2,
    "boost_on_errors": false,
    "kmeans_features": false,
    "mix_encoding": false,
    "max_single_prediction_time": 0.5,
    "n_jobs": -1,
    "random_state": 1234,
    "saved": [
        "1_Default_Xgboost",
        "2_Default_CatBoost",
        "3_Default_RandomForest",
        "4_Xgboost",
        "8_CatBoost",
        "12_RandomForest",
        "5_Xgboost",
        "9_CatBoost",
        "13_RandomForest",
        "6_Xgboost",
        "10_CatBoost",
        "14_RandomForest",
        "7_Xgboost",
        "11_CatBoost",
        "15_RandomForest",
        "16_CatBoost",
        "17_CatBoost",
        "18_CatBoost",
        "19_RandomForest",
        "20_RandomForest",
        "21_Xgboost",
        "22_Xgboost",
        "23_Xgboost",
        "24_CatBoost",
        "26_RandomForest",
        "Ensemble"
    ],
    "fit_level": "finished",
    "best_model": "Ensemble",
    "load_on_predict": [
        "11_CatBoost",
        "17_CatBoost",
        "26_RandomForest",
        "9_CatBoost",
        "Ensemble"
    ]
}